binance/__init__.py
binance/__version__.py
binance/api.py
binance/error.py
binance/lib/__init__.py
binance/lib/enums.py
binance/lib/utils.py
binance/spot/__init__.py
binance/spot/account.py
binance/spot/blvt.py
binance/spot/bswap.py
binance/spot/c2c.py
binance/spot/convert.py
binance/spot/data_stream.py
binance/spot/fiat.py
binance/spot/futures.py
binance/spot/loan.py
binance/spot/margin.py
binance/spot/market.py
binance/spot/mining.py
binance/spot/nft.py
binance/spot/pay.py
binance/spot/rebate.py
binance/spot/savings.py
binance/spot/sub_account.py
binance/spot/wallet.py
binance/websocket/__init__.py
binance/websocket/binance_client_factory.py
binance/websocket/binance_client_protocol.py
binance/websocket/binance_socket_manager.py
binance/websocket/websocket_client.py
binance/websocket/spot/__init__.py
binance/websocket/spot/websocket_client.py
aisling_connector-2.dist-info/LICENSE.md
aisling_connector-2.dist-info/METADATA
aisling_connector-2.dist-info/WHEEL
aisling_connector-2.dist-info/top_level.txt
aisling_connector-2.dist-info/RECORD
