Metadata-Version: 2.1
Name: aisling-connector
Version: 2
Summary: This is a lightweight library that works as a connector to Binance public API.
Home-page: https://github.com/aisling11/connector
License: MIT
Keywords: Binance,Public API
Platform: UNKNOWN
Classifier: Intended Audience :: Developers
Classifier: Intended Audience :: Financial and Insurance Industry
Classifier: License :: OSI Approved :: MIT License
Classifier: Programming Language :: Python :: 3.6
Classifier: Programming Language :: Python :: 3.7
Classifier: Programming Language :: Python :: 3.8
Classifier: Programming Language :: Python :: 3.9
Classifier: Programming Language :: Python :: 3.10
Requires-Python: >=3.6
License-File: LICENSE.md
Requires-Dist: autobahn (>=21.2.1)
Requires-Dist: Twisted (>=21.2.0)
Requires-Dist: requests (>=2.25.1)
Requires-Dist: pyOpenSSL (>=19.0.0)
Requires-Dist: service-identity (>=21.1.0)
